git_anon/__init__.py
git_anon/anon_config.py
git_anon/anon_identity.py
git_anon/api_functions.py
git_anon/custom_exception.py
git_anon/git_hooks.py
git_anon/identity.py
git_anon/git_config/__init__.py
git_anon/gpg_general/__init__.py
git_anon/gpg_general/key_utils.py
git_anon/keystores/__init__.py
git_anon/keystores/gpg_keystore.py
git_anon/keystores/gpg_keystore_combined.py
git_anon/keystores/gpg_keystore_personal.py
git_anon/keystores/gpg_keystore_shared.py
git_anon/keystores/gpg_keystore_trusted.py
git_anon/keystores/gpg_keystore_unencrypted.py
git_anon/library_patches/__init__.py
git_anon/library_patches/patched_pgpy_functions.py
git_anon/system_interactions/__init__.py
git_anon/system_interactions/subprocess_utils.py
git_anon_cli/__init__.py
gpg_replacement/__init__.py
git_anon-0.1.1.dist-info/LICENSE.txt
git_anon-0.1.1.dist-info/METADATA
git_anon-0.1.1.dist-info/WHEEL
git_anon-0.1.1.dist-info/entry_points.txt
git_anon-0.1.1.dist-info/top_level.txt
git_anon-0.1.1.dist-info/RECORD
