Metadata-Version: 2.1
Name: git-anon
Version: 0.1.1
Summary: Anonymous Git with Signatures
Home-page: https://github.com/erikescher/git-anon
Author: Erik Escher
Author-email: git-anon@erikescher.de
License: MIT
Keywords: git,gpg,anonymity
Platform: UNKNOWN
Classifier: Development Status :: 3 - Alpha
Classifier: Environment :: Console
Classifier: Intended Audience :: Developers
Classifier: Intended Audience :: Information Technology
Classifier: License :: OSI Approved
Classifier: License :: OSI Approved :: MIT License
Classifier: Natural Language :: English
Classifier: Operating System :: Unix
Classifier: Operating System :: POSIX :: Linux
Classifier: Programming Language :: Python
Classifier: Programming Language :: Python :: 3
Classifier: Programming Language :: Python :: 3 :: Only
Classifier: Programming Language :: Python :: 3.8
Classifier: Programming Language :: Python :: 3.9
Classifier: Topic :: Security :: Cryptography
Classifier: Topic :: Software Development
Classifier: Topic :: Software Development :: Version Control
Classifier: Topic :: Software Development :: Version Control :: Git
Classifier: Typing :: Typed
Requires-Python: >=3.8
Requires-Dist: click (>=7.0)
Requires-Dist: GitPython (>=2.1.15)
Requires-Dist: PGPy (>=0.5.0)
Requires-Dist: cryptography (>=3.1)
